<?xml version="1.0" encoding="utf-8"?>
<!DOCTYPE hibernate-mapping PUBLIC "-//Hibernate/Hibernate Mapping DTD 3.0//EN"
"http://hibernate.sourceforge.net/hibernate-mapping-3.0.dtd">
<!-- 
    Mapping file autogenerated by MyEclipse Persistence Tools
-->
<hibernate-mapping>
<class name="com.entity.Ticket" table="ticket_info" catalog="db_movie">
<id name="ticket_id" >
  <column name="ticket_id">  
  </column>
  <generator class="assigned"></generator>
</id>
<!-- <property name="stuid" type="java.lang.Integer">
<column name="stuid" length="20"></column>
</property> -->
<property name="code" type="java.lang.String">
<column name="code" length="50"></column>
</property>
<property name="u_seat" type="java.lang.String">
<column name="u_seat" length="45"></column>
</property>
<property name="currPrice" type="java.lang.Double">
<column name="currPrice" length="10"></column>
</property>
<property name="date" type="java.lang.String">
<column name="date" length="20"></column>
</property>
<property name="statue" type="java.lang.Integer">
<column name="statue" length="2"></column>
</property>
<!-- 其中的name要在Ticket实体类中为Play的一个实例对象 -->
<!-- 电影票的某个场次可卖多张 -->
<many-to-one name="play"
 class="com.entity.Play"
 cascade="none"
 outer-join="auto"
 update="true"
 insert="true"
 access="property"
 column="play_id"
 not-null="true"
 lazy="false"
></many-to-one>
<!-- 多张电影票可被同一个用户拥有 -->
<many-to-one name="user"
class="com.entity.User"
cascade="none"
outer-join="auto"
update="true"
insert="true"
access="property"
column="user_id"
not-null="true"
lazy="false"
>
</many-to-one>
<!-- <set name="userInfo" table="user_info" cascade="all-delete-orphan" 
            lazy="true" inverse="true">
            <key column="good_id" />确定关联的外键列
            <one-to-many class="com.entity.UserInfo"  />
</set> -->
</class>
</hibernate-mapping>